COPYING
COPYING.LESSER
Changelog
MANIFEST.in
README.rst
check.py
clean.py
distribute_setup.py
requirements.txt
setup.py
StarCluster_openstack.egg-info/PKG-INFO
StarCluster_openstack.egg-info/SOURCES.txt
StarCluster_openstack.egg-info/dependency_links.txt
StarCluster_openstack.egg-info/top_level.txt
bin/sccleanup
bin/starcluster
completion/README.rst
completion/starcluster-completion.sh
docs/epydoc/build.sh
docs/epydoc/epydoc.css
docs/epydoc/scepydoc.conf
docs/sphinx/Makefile
docs/sphinx/TODO.rst
docs/sphinx/changelog.rst
docs/sphinx/conf.py
docs/sphinx/contents.rst
docs/sphinx/contribute.rst
docs/sphinx/faq.rst
docs/sphinx/features.rst
docs/sphinx/hacking.rst
docs/sphinx/index.rst
docs/sphinx/installation.rst
docs/sphinx/license.rst
docs/sphinx/make.bat
docs/sphinx/overview.rst
docs/sphinx/quickstart.rst
docs/sphinx/support.rst
docs/sphinx/_static/balancer_decision_diagram.jpg
docs/sphinx/_static/balancer_visualizer.png
docs/sphinx/_static/forkproject.png
docs/sphinx/_static/hadoopnamenode.png
docs/sphinx/_static/hadooptracker.png
docs/sphinx/_static/ipnotebookbusy.png
docs/sphinx/_static/ipnotebookbusy.svg
docs/sphinx/_static/ipnotebookdashboard.png
docs/sphinx/_static/ipnotebookdownload.png
docs/sphinx/_static/ipnotebooklogin.png
docs/sphinx/_static/ipnotebooknew.png
docs/sphinx/_static/ipnotebookparallel.png
docs/sphinx/_static/ipnotebookrename.png
docs/sphinx/_static/logo-small.png
docs/sphinx/_static/logo.png
docs/sphinx/_static/scoverview.png
docs/sphinx/_static/scoverview.svg
docs/sphinx/_static/spothistory.png
docs/sphinx/_static/starcluster.ico
docs/sphinx/_static/tmuxcc.png
docs/sphinx/_templates/index.html
docs/sphinx/_templates/indexsidebar.html
docs/sphinx/_templates/layout.html
docs/sphinx/_themes/pylons_theme_support.py
docs/sphinx/_themes/pylons/layout.html
docs/sphinx/_themes/pylons/theme.conf
docs/sphinx/_themes/pylons/static/Neuton-webfont.svg
docs/sphinx/_themes/pylons/static/Neuton-webfont.ttf
docs/sphinx/_themes/pylons/static/Neuton-webfont.woff
docs/sphinx/_themes/pylons/static/dialog-note.png
docs/sphinx/_themes/pylons/static/dialog-seealso.png
docs/sphinx/_themes/pylons/static/dialog-topic.png
