Metadata-Version: 1.0
Name: StarCluster-openstack
Version: 0.94.3-openstack
Summary: This is an OpenStack port of StarCluster developed by MIT (http://star.mit.edu/cluster)
Home-page: http://github.com/shundezhang/starcluster
Author: Shunde Zhang
Author-email: shunde.zhang@ersa.edu.au
License: LGPL3
Platform: UNKNOWN
Classifier: Environment :: Console
Classifier: Development Status :: 4 - Beta
Classifier: Intended Audience :: Developers
Classifier: Intended Audience :: Education
Classifier: Intended Audience :: System Administrators
Classifier: Intended Audience :: Other Audience
Classifier: Intended Audience :: Science/Research
Classifier: License :: OSI Approved :: GNU Library or Lesser General Public License (LGPL)
Classifier: Natural Language :: English
Classifier: Programming Language :: Python
Classifier: Programming Language :: Python :: 2.6
Classifier: Programming Language :: Python :: 2.7
Classifier: Operating System :: OS Independent
Classifier: Operating System :: POSIX
Classifier: Topic :: Education
Classifier: Topic :: Scientific/Engineering
Classifier: Topic :: System :: Distributed Computing
Classifier: Topic :: System :: Clustering
Classifier: Topic :: Software Development :: Libraries :: Python Modules
